eden/__init__.py
eden/block.py
eden/celery_utils.py
eden/client.py
eden/config_wrapper.py
eden/data_handlers.py
eden/datatypes.py
eden/gpu_allocator.py
eden/hosting.py
eden/image_utils.py
eden/log_utils.py
eden/models.py
eden/progress_tracker.py
eden/prometheus_utils.py
eden/queue.py
eden/result_storage.py
eden/threaded_server.py
eden/utils.py
eden/tests/__init__.py
eden/tests/server.py
eden/tests/start_server.py
eden/tests/stop_server.py
eden/tests/test_block.py
eden/tests/test_data_types.py
eden/tests/test_queue.py
eden/tests/test_result_storage.py
eden/tests/test_schemas.py
eden/tests/test_update_config.py
eden_python-0.2.0.dist-info/LICENSE
eden_python-0.2.0.dist-info/METADATA
eden_python-0.2.0.dist-info/WHEEL
eden_python-0.2.0.dist-info/top_level.txt
eden_python-0.2.0.dist-info/RECORD
