Metadata-Version: 2.1
Name: eden-python
Version: 0.2.0
Summary: Convert your python function into a hosted endpoint with minimal changes to your existing code
Home-page: https://github.com/abraham-ai/eden
Author: Mayukh Deb, Gene Kogan
Author-email: mayukhmainak2000@gmail.com, kogan.gene@gmail.com
License: UNKNOWN
Keywords: hosting,machine learning,neural networks,generative art
Platform: UNKNOWN
Classifier: Natural Language :: English
Classifier: Programming Language :: Python :: 3.6
Requires-Python: >=3.6
License-File: LICENSE
Requires-Dist: amqp (==5.1.1)
Requires-Dist: async-timeout (==4.0.2)
Requires-Dist: billiard (==3.6.4.0)
Requires-Dist: celery (==5.2.7)
Requires-Dist: certifi (==2022.6.15)
Requires-Dist: charset-normalizer (==2.1.0)
Requires-Dist: click (==8.1.3)
Requires-Dist: click-didyoumean (==0.3.0)
Requires-Dist: click-plugins (==1.1.1)
Requires-Dist: click-repl (==0.2.0)
Requires-Dist: deprecated (==1.2.13)
Requires-Dist: fastapi (==0.68.1)
Requires-Dist: gitdb (==4.0.9)
Requires-Dist: gitpython (==3.1.27)
Requires-Dist: h11 (==0.13.0)
Requires-Dist: idna (==3.3)
Requires-Dist: kombu (==5.2.4)
Requires-Dist: numpy (==1.23.1)
Requires-Dist: nvidia-ml-py3 (==7.352.0)
Requires-Dist: opencv-python (==4.6.0.66)
Requires-Dist: packaging (==21.3)
Requires-Dist: pillow (==9.2.0)
Requires-Dist: prometheus-client (==0.14.1)
Requires-Dist: prompt-toolkit (==3.0.30)
Requires-Dist: pydantic (==1.8.2)
Requires-Dist: pyparsing (==3.0.9)
Requires-Dist: pytz (==2022.1)
Requires-Dist: redis (==4.3.4)
Requires-Dist: requests (==2.28.1)
Requires-Dist: six (==1.16.0)
Requires-Dist: smmap (==5.0.0)
Requires-Dist: starlette (==0.14.2)
Requires-Dist: starlette-exporter (==0.13.0)
Requires-Dist: tqdm (==4.64.0)
Requires-Dist: typing-extensions (==3.10.0.2)
Requires-Dist: urllib3 (==1.26.11)
Requires-Dist: uvicorn (==0.18.2)
Requires-Dist: vine (==5.0.0)
Requires-Dist: wcwidth (==0.2.5)
Requires-Dist: wrapt (==1.14.1)
